easyThreading/__init__.py
easyThreading-0.1.0.dist-info/METADATA
easyThreading-0.1.0.dist-info/RECORD
easyThreading-0.1.0.dist-info/WHEEL
easyThreading-0.1.0.dist-info/top_level.txt
easyThreading-0.1.0.dist-info/zip-safe
