Metadata-Version: 2.1
Name: easyThreading
Version: 0.1.0
Summary: a userf-friendly interface threading management library
Home-page: https://github.com/JacksonWuxs/easyThreading
Author: Xuansheng Wu
Author-email: wuxsmail@163.com
Maintainer: Xuansheng Wu
Maintainer-email: wuxsmail@163.com
License: GPL v3
Platform: all
Classifier: Development Status :: 3 - Alpha
Classifier: Intended Audience :: Developers
Classifier: License :: OSI Approved :: GNU General Public License v3 (GPLv3)
Classifier: Programming Language :: Python :: 2
Classifier: Programming Language :: Python :: 3
Classifier: Intended Audience :: Developers
Classifier: Operating System :: OS Independent
